agentjo/__init__.py
agentjo/agent.py
agentjo/function.py
agentjo/memory.py
agentjo/ranker.py
agentjo/utils.py
agentjo/agent_wrapper/__init__.py
agentjo/agent_wrapper/conversation.py
agentjo/memory_classes/__init__.py
agentjo/memory_classes/sqlite_memory.py
agentjo-1.1.0.dist-info/licenses/LICENSE
agentjo-1.1.0.dist-info/METADATA
agentjo-1.1.0.dist-info/WHEEL
agentjo-1.1.0.dist-info/top_level.txt
agentjo-1.1.0.dist-info/RECORD
