Metadata-Version: 2.4
Name: agentjo
Version: 1.1.0
Summary: Towards Human-Friendly, Fast Learning and Adaptable Agent Communities
Author-email: John Tan Chong Min <tanchongmin@gmail.com>
License-Expression: MIT
Project-URL: Homepage, https://github.com/tanchongmin/agentjo
Project-URL: Issues, https://github.com/tanchongmin/agentjo/issues
Classifier: Programming Language :: Python :: 3
Classifier: Operating System :: OS Independent
Requires-Python: >=3.8
License-File: LICENSE
Requires-Dist: strictjson>=6.1.2
Requires-Dist: openai>=1.3.6
Requires-Dist: dill>=0.3.7
Requires-Dist: termcolor>=2.3.0
Requires-Dist: requests
Requires-Dist: pandas
Requires-Dist: pydantic
Provides-Extra: full
Requires-Dist: PyPDF2; extra == "full"
Requires-Dist: python-docx; extra == "full"
Requires-Dist: xlrd; extra == "full"
Requires-Dist: sentence_transformers; extra == "full"
Dynamic: license-file
